{
  "schema_version": "v1",
  "generated_at": "2026-05-13T23:46:26Z",
  "families": {
    "attention_sentiment": {
      "family": "attention_sentiment",
      "count": 26,
      "by_status": {
        "live_only": 10,
        "parked": 2,
        "sandbox": 14
      },
      "by_evidence_class": {
        "live_receipts_only": 10,
        "needs_history": 14,
        "pending_seed": 2
      },
      "leaders": [
        {
          "schema_version": "v1",
          "key": "crazy:price-momentum-reversion-in-defensive-sectors-after-tech-cra",
          "algo_type": "crazy",
          "algo_id": "price-momentum-reversion-in-defensive-sectors-after-tech-cra",
          "name": "Price Momentum Reversion In Defensive Sectors After Tech Crash",
          "family": "attention_sentiment",
          "status": "live_only",
          "evidence_class": "live_receipts_only",
          "rebalance_frequency": "daily",
          "ytd_pct": 0.06,
          "days_running": 77,
          "beat_spy": false,
          "spy_pct": 8.95,
          "alpha_pct": -8.89,
          "ret_30d_pct": 0.06,
          "spy_delta_30d_pct": -8.13,
          "last_snapshot": "2026-05-13",
          "new_algo_date": null,
          "comparator": {
            "primary_etf": "XLK",
            "signals": {
              "momentum_5d": {
                "direction": "UP",
                "confidence": 0.802,
                "return_pct": 4.011
              },
              "momentum_20d": {
                "direction": "UP",
                "confidence": 1.0,
                "return_pct": 17.665
              }
            },
            "summary": "both_up"
          }
        },
        {
          "schema_version": "v1",
          "key": "crazy:reddit-sentiment-spike",
          "algo_type": "crazy",
          "algo_id": "reddit-sentiment-spike",
          "name": "Reddit Sentiment Spike",
          "family": "attention_sentiment",
          "status": "sandbox",
          "evidence_class": "needs_history",
          "rebalance_frequency": "daily",
          "ytd_pct": 0.0,
          "days_running": 98,
          "beat_spy": false,
          "spy_pct": 8.95,
          "alpha_pct": -8.95,
          "ret_30d_pct": 0.0,
          "spy_delta_30d_pct": -8.19,
          "last_snapshot": "2026-05-13",
          "new_algo_date": null,
          "comparator": null
        },
        {
          "schema_version": "v1",
          "key": "crazy:reddit-mentions-volatility-spike",
          "algo_type": "crazy",
          "algo_id": "reddit-mentions-volatility-spike",
          "name": "Reddit Mentions Volatility Spike",
          "family": "attention_sentiment",
          "status": "sandbox",
          "evidence_class": "needs_history",
          "rebalance_frequency": "daily",
          "ytd_pct": 0.0,
          "days_running": 98,
          "beat_spy": false,
          "spy_pct": 8.95,
          "alpha_pct": -8.95,
          "ret_30d_pct": 0.0,
          "spy_delta_30d_pct": -8.19,
          "last_snapshot": "2026-05-13",
          "new_algo_date": null,
          "comparator": null
        },
        {
          "schema_version": "v1",
          "key": "crazy:reddit-gaming-thread-spike",
          "algo_type": "crazy",
          "algo_id": "reddit-gaming-thread-spike",
          "name": "Reddit Gaming Thread Spike",
          "family": "attention_sentiment",
          "status": "sandbox",
          "evidence_class": "needs_history",
          "rebalance_frequency": "daily",
          "ytd_pct": 0.0,
          "days_running": 98,
          "beat_spy": false,
          "spy_pct": 8.95,
          "alpha_pct": -8.95,
          "ret_30d_pct": 0.0,
          "spy_delta_30d_pct": -8.19,
          "last_snapshot": "2026-05-13",
          "new_algo_date": null,
          "comparator": null
        },
        {
          "schema_version": "v1",
          "key": "crazy:reddit-emoji-sentiment-spike",
          "algo_type": "crazy",
          "algo_id": "reddit-emoji-sentiment-spike",
          "name": "Reddit Emoji Sentiment Spike",
          "family": "attention_sentiment",
          "status": "sandbox",
          "evidence_class": "needs_history",
          "rebalance_frequency": "daily",
          "ytd_pct": 0.0,
          "days_running": 98,
          "beat_spy": false,
          "spy_pct": 8.95,
          "alpha_pct": -8.95,
          "ret_30d_pct": 0.0,
          "spy_delta_30d_pct": -8.19,
          "last_snapshot": "2026-05-13",
          "new_algo_date": null,
          "comparator": null
        }
      ]
    },
    "consumer_stress": {
      "family": "consumer_stress",
      "count": 60,
      "by_status": {
        "failed": 1,
        "live_only": 28,
        "sandbox": 31
      },
      "by_evidence_class": {
        "live_receipts_only": 28,
        "needs_history": 31,
        "v1_backtested": 1
      },
      "leaders": [
        {
          "schema_version": "v1",
          "key": "crazy:retail-sales-momentum",
          "algo_type": "crazy",
          "algo_id": "retail-sales-momentum",
          "name": "Retail Sales Momentum",
          "family": "consumer_stress",
          "status": "live_only",
          "evidence_class": "live_receipts_only",
          "rebalance_frequency": "monthly",
          "ytd_pct": 4.15,
          "days_running": 98,
          "beat_spy": false,
          "spy_pct": 8.95,
          "alpha_pct": -4.81,
          "ret_30d_pct": 4.15,
          "spy_delta_30d_pct": -4.05,
          "last_snapshot": "2026-05-13",
          "new_algo_date": null,
          "comparator": null
        },
        {
          "schema_version": "v1",
          "key": "crazy:weekly-surge-in-google-trends-searches-for-diy-electronics-r",
          "algo_type": "crazy",
          "algo_id": "weekly-surge-in-google-trends-searches-for-diy-electronics-r",
          "name": "Weekly Surge In Google Trends Searches For Diy Electronics Repair Signals Bullish Xlk",
          "family": "consumer_stress",
          "status": "live_only",
          "evidence_class": "live_receipts_only",
          "rebalance_frequency": "weekly",
          "ytd_pct": 0.08,
          "days_running": 84,
          "beat_spy": false,
          "spy_pct": 8.95,
          "alpha_pct": -8.87,
          "ret_30d_pct": 0.08,
          "spy_delta_30d_pct": -8.11,
          "last_snapshot": "2026-05-13",
          "new_algo_date": null,
          "comparator": {
            "primary_etf": "XLK",
            "signals": {
              "momentum_5d": {
                "direction": "UP",
                "confidence": 0.802,
                "return_pct": 4.011
              },
              "momentum_20d": {
                "direction": "UP",
                "confidence": 1.0,
                "return_pct": 17.665
              }
            },
            "summary": "both_up"
          }
        },
        {
          "schema_version": "v1",
          "key": "crazy:weekly-google-trends-surge-in-diy-electronics-repair-signals",
          "algo_type": "crazy",
          "algo_id": "weekly-google-trends-surge-in-diy-electronics-repair-signals",
          "name": "Weekly Google Trends Surge In Diy Electronics Repair Signals Tech Consumer Stress Lift",
          "family": "consumer_stress",
          "status": "live_only",
          "evidence_class": "live_receipts_only",
          "rebalance_frequency": "weekly",
          "ytd_pct": 0.08,
          "days_running": 80,
          "beat_spy": false,
          "spy_pct": 8.95,
          "alpha_pct": -8.87,
          "ret_30d_pct": 0.18,
          "spy_delta_30d_pct": -8.01,
          "last_snapshot": "2026-05-13",
          "new_algo_date": null,
          "comparator": {
            "primary_etf": "XLK",
            "signals": {
              "momentum_5d": {
                "direction": "UP",
                "confidence": 0.802,
                "return_pct": 4.011
              },
              "momentum_20d": {
                "direction": "UP",
                "confidence": 1.0,
                "return_pct": 17.665
              }
            },
            "summary": "both_up"
          }
        },
        {
          "schema_version": "v1",
          "key": "crazy:daily-jump-in-consumer-stress-google-trends-searches-for-car",
          "algo_type": "crazy",
          "algo_id": "daily-jump-in-consumer-stress-google-trends-searches-for-car",
          "name": "Daily Jump In Consumer Stress Google Trends Searches For Car Repossession Signals Rising Financial Distress",
          "family": "consumer_stress",
          "status": "live_only",
          "evidence_class": "live_receipts_only",
          "rebalance_frequency": "daily",
          "ytd_pct": 0.07,
          "days_running": 69,
          "beat_spy": false,
          "spy_pct": 8.95,
          "alpha_pct": -8.88,
          "ret_30d_pct": -0.04,
          "spy_delta_30d_pct": -8.24,
          "last_snapshot": "2026-05-13",
          "new_algo_date": null,
          "comparator": {
            "primary_etf": "XLY",
            "signals": {
              "momentum_5d": {
                "direction": "DOWN",
                "confidence": 0.192,
                "return_pct": -0.959
              },
              "momentum_20d": {
                "direction": "UP",
                "confidence": 0.091,
                "return_pct": 0.457
              }
            },
            "summary": "mixed"
          }
        },
        {
          "schema_version": "v1",
          "key": "crazy:google-trends-surge-in-used-car-price-searches",
          "algo_type": "crazy",
          "algo_id": "google-trends-surge-in-used-car-price-searches",
          "name": "Google Trends Surge In Used Car Price Searches",
          "family": "consumer_stress",
          "status": "live_only",
          "evidence_class": "live_receipts_only",
          "rebalance_frequency": "weekly",
          "ytd_pct": 0.04,
          "days_running": 78,
          "beat_spy": false,
          "spy_pct": 8.95,
          "alpha_pct": -8.92,
          "ret_30d_pct": 0.0,
          "spy_delta_30d_pct": -8.19,
          "last_snapshot": "2026-05-13",
          "new_algo_date": null,
          "comparator": {
            "primary_etf": "XLY",
            "signals": {
              "momentum_5d": {
                "direction": "DOWN",
                "confidence": 0.192,
                "return_pct": -0.959
              },
              "momentum_20d": {
                "direction": "UP",
                "confidence": 0.091,
                "return_pct": 0.457
              }
            },
            "summary": "mixed"
          }
        }
      ]
    },
    "core_rotation": {
      "family": "core_rotation",
      "count": 5,
      "by_status": {
        "promoted": 5
      },
      "by_evidence_class": {
        "live_receipts_only": 2,
        "v1_backtested": 3
      },
      "leaders": [
        {
          "schema_version": "v1",
          "key": "normal:simple_monthly",
          "algo_type": "normal",
          "algo_id": "simple_monthly",
          "name": "Quantified Simple Monthly Rotation",
          "family": "core_rotation",
          "status": "promoted",
          "evidence_class": "live_receipts_only",
          "rebalance_frequency": "monthly_eom",
          "ytd_pct": 10.87,
          "days_running": 99,
          "beat_spy": true,
          "spy_pct": 8.95,
          "alpha_pct": 1.91,
          "ret_30d_pct": 10.87,
          "spy_delta_30d_pct": 2.67,
          "last_snapshot": "2026-05-13",
          "new_algo_date": null,
          "comparator": null
        },
        {
          "schema_version": "v1",
          "key": "normal:baileymol",
          "algo_type": "normal",
          "algo_id": "baileymol",
          "name": "Algo Baileymol (Chaos Monger)",
          "family": "core_rotation",
          "status": "promoted",
          "evidence_class": "v1_backtested",
          "rebalance_frequency": "weekly",
          "ytd_pct": 7.61,
          "days_running": 99,
          "beat_spy": false,
          "spy_pct": 8.95,
          "alpha_pct": -1.34,
          "ret_30d_pct": 3.8,
          "spy_delta_30d_pct": -4.4,
          "last_snapshot": "2026-05-13",
          "new_algo_date": null,
          "comparator": null
        },
        {
          "schema_version": "v1",
          "key": "normal:faber",
          "algo_type": "normal",
          "algo_id": "faber",
          "name": "Faber Momentum Rotation",
          "family": "core_rotation",
          "status": "promoted",
          "evidence_class": "v1_backtested",
          "rebalance_frequency": "monthly_eom",
          "ytd_pct": 6.42,
          "days_running": 99,
          "beat_spy": false,
          "spy_pct": 8.95,
          "alpha_pct": -2.53,
          "ret_30d_pct": 2.48,
          "spy_delta_30d_pct": -5.71,
          "last_snapshot": "2026-05-13",
          "new_algo_date": null,
          "comparator": null
        },
        {
          "schema_version": "v1",
          "key": "normal:dmsr",
          "algo_type": "normal",
          "algo_id": "dmsr",
          "name": "Antonacci Dual Momentum Sector Rotation",
          "family": "core_rotation",
          "status": "promoted",
          "evidence_class": "live_receipts_only",
          "rebalance_frequency": "monthly_eom",
          "ytd_pct": 5.78,
          "days_running": 99,
          "beat_spy": false,
          "spy_pct": 8.95,
          "alpha_pct": -3.18,
          "ret_30d_pct": 3.02,
          "spy_delta_30d_pct": -5.17,
          "last_snapshot": "2026-05-13",
          "new_algo_date": null,
          "comparator": null
        },
        {
          "schema_version": "v1",
          "key": "normal:biscotti",
          "algo_type": "normal",
          "algo_id": "biscotti",
          "name": "Algo Biscotti (Unconditional Loyalty)",
          "family": "core_rotation",
          "status": "promoted",
          "evidence_class": "v1_backtested",
          "rebalance_frequency": "monthly_eom",
          "ytd_pct": -2.09,
          "days_running": 99,
          "beat_spy": false,
          "spy_pct": 8.95,
          "alpha_pct": -11.05,
          "ret_30d_pct": -1.22,
          "spy_delta_30d_pct": -9.41,
          "last_snapshot": "2026-05-13",
          "new_algo_date": null,
          "comparator": null
        }
      ]
    },
    "freight_logistics": {
      "family": "freight_logistics",
      "count": 14,
      "by_status": {
        "live_only": 9,
        "sandbox": 5
      },
      "by_evidence_class": {
        "live_receipts_only": 9,
        "needs_history": 5
      },
      "leaders": [
        {
          "schema_version": "v1",
          "key": "crazy:freight-rail-carloads",
          "algo_type": "crazy",
          "algo_id": "freight-rail-carloads",
          "name": "Freight Rail Carloads",
          "family": "freight_logistics",
          "status": "live_only",
          "evidence_class": "live_receipts_only",
          "rebalance_frequency": "monthly",
          "ytd_pct": 0.64,
          "days_running": 98,
          "beat_spy": false,
          "spy_pct": 8.95,
          "alpha_pct": -8.32,
          "ret_30d_pct": 0.64,
          "spy_delta_30d_pct": -7.56,
          "last_snapshot": "2026-05-13",
          "new_algo_date": null,
          "comparator": null
        },
        {
          "schema_version": "v1",
          "key": "crazy:truck-tonnage",
          "algo_type": "crazy",
          "algo_id": "truck-tonnage",
          "name": "Truck Tonnage Index",
          "family": "freight_logistics",
          "status": "live_only",
          "evidence_class": "live_receipts_only",
          "rebalance_frequency": "monthly",
          "ytd_pct": 0.55,
          "days_running": 98,
          "beat_spy": false,
          "spy_pct": 8.95,
          "alpha_pct": -8.41,
          "ret_30d_pct": 0.55,
          "spy_delta_30d_pct": -7.65,
          "last_snapshot": "2026-05-13",
          "new_algo_date": null,
          "comparator": null
        },
        {
          "schema_version": "v1",
          "key": "crazy:weekly-spike-in-google-trends-searches-for-warehouse-automat",
          "algo_type": "crazy",
          "algo_id": "weekly-spike-in-google-trends-searches-for-warehouse-automat",
          "name": "Weekly Spike In Google Trends Searches For Warehouse Automation Failure Signals Bearish Xli",
          "family": "freight_logistics",
          "status": "live_only",
          "evidence_class": "live_receipts_only",
          "rebalance_frequency": "weekly",
          "ytd_pct": 0.04,
          "days_running": 84,
          "beat_spy": false,
          "spy_pct": 8.95,
          "alpha_pct": -8.91,
          "ret_30d_pct": 0.04,
          "spy_delta_30d_pct": -8.15,
          "last_snapshot": "2026-05-13",
          "new_algo_date": null,
          "comparator": {
            "primary_etf": "XLI",
            "signals": {
              "momentum_5d": {
                "direction": "DOWN",
                "confidence": 0.368,
                "return_pct": -1.838
              },
              "momentum_20d": {
                "direction": "UP",
                "confidence": 0.285,
                "return_pct": 1.425
              }
            },
            "summary": "mixed"
          }
        },
        {
          "schema_version": "v1",
          "key": "crazy:daily-spike-in-freight-logistics-rss-news-volume-mentioning-",
          "algo_type": "crazy",
          "algo_id": "daily-spike-in-freight-logistics-rss-news-volume-mentioning-",
          "name": "Daily Spike In Freight Logistics Rss News Volume Mentioning Port Labor Strike Triggers Bearish Xli",
          "family": "freight_logistics",
          "status": "sandbox",
          "evidence_class": "needs_history",
          "rebalance_frequency": "daily",
          "ytd_pct": 0.0,
          "days_running": 84,
          "beat_spy": false,
          "spy_pct": 8.95,
          "alpha_pct": -8.95,
          "ret_30d_pct": 0.0,
          "spy_delta_30d_pct": -8.19,
          "last_snapshot": "2026-05-13",
          "new_algo_date": null,
          "comparator": {
            "primary_etf": "XLI",
            "signals": {
              "momentum_5d": {
                "direction": "DOWN",
                "confidence": 0.368,
                "return_pct": -1.838
              },
              "momentum_20d": {
                "direction": "UP",
                "confidence": 0.285,
                "return_pct": 1.425
              }
            },
            "summary": "mixed"
          }
        },
        {
          "schema_version": "v1",
          "key": "crazy:cardboard",
          "algo_type": "crazy",
          "algo_id": "cardboard",
          "name": "Cardboard Box Index",
          "family": "freight_logistics",
          "status": "sandbox",
          "evidence_class": "needs_history",
          "rebalance_frequency": "monthly",
          "ytd_pct": 0.0,
          "days_running": 98,
          "beat_spy": false,
          "spy_pct": 8.95,
          "alpha_pct": -8.95,
          "ret_30d_pct": 0.0,
          "spy_delta_30d_pct": -8.19,
          "last_snapshot": "2026-05-13",
          "new_algo_date": null,
          "comparator": null
        }
      ]
    },
    "labor_jobs": {
      "family": "labor_jobs",
      "count": 15,
      "by_status": {
        "live_only": 7,
        "sandbox": 8
      },
      "by_evidence_class": {
        "live_receipts_only": 7,
        "needs_history": 8
      },
      "leaders": [
        {
          "schema_version": "v1",
          "key": "crazy:job-posting-acceleration",
          "algo_type": "crazy",
          "algo_id": "job-posting-acceleration",
          "name": "Job Posting Acceleration",
          "family": "labor_jobs",
          "status": "live_only",
          "evidence_class": "live_receipts_only",
          "rebalance_frequency": "monthly",
          "ytd_pct": 2.54,
          "days_running": 98,
          "beat_spy": false,
          "spy_pct": 8.95,
          "alpha_pct": -6.41,
          "ret_30d_pct": 2.54,
          "spy_delta_30d_pct": -5.65,
          "last_snapshot": "2026-05-13",
          "new_algo_date": null,
          "comparator": null
        },
        {
          "schema_version": "v1",
          "key": "crazy:recession-whisper-google-trends-unemployment-search-surge",
          "algo_type": "crazy",
          "algo_id": "recession-whisper-google-trends-unemployment-search-surge",
          "name": "Recession Whisper Google Trends Unemployment Search Surge",
          "family": "labor_jobs",
          "status": "live_only",
          "evidence_class": "live_receipts_only",
          "rebalance_frequency": "weekly",
          "ytd_pct": 0.07,
          "days_running": 80,
          "beat_spy": false,
          "spy_pct": 8.95,
          "alpha_pct": -8.88,
          "ret_30d_pct": 0.0,
          "spy_delta_30d_pct": -8.19,
          "last_snapshot": "2026-05-13",
          "new_algo_date": null,
          "comparator": {
            "primary_etf": "XLY",
            "signals": {
              "momentum_5d": {
                "direction": "DOWN",
                "confidence": 0.192,
                "return_pct": -0.959
              },
              "momentum_20d": {
                "direction": "UP",
                "confidence": 0.091,
                "return_pct": 0.457
              }
            },
            "summary": "mixed"
          }
        },
        {
          "schema_version": "v1",
          "key": "crazy:linkedin",
          "algo_type": "crazy",
          "algo_id": "linkedin",
          "name": "LinkedIn Layoff Propagation",
          "family": "labor_jobs",
          "status": "sandbox",
          "evidence_class": "needs_history",
          "rebalance_frequency": "monthly",
          "ytd_pct": 0.0,
          "days_running": 98,
          "beat_spy": false,
          "spy_pct": 8.95,
          "alpha_pct": -8.95,
          "ret_30d_pct": 0.0,
          "spy_delta_30d_pct": -8.19,
          "last_snapshot": "2026-05-13",
          "new_algo_date": null,
          "comparator": null
        },
        {
          "schema_version": "v1",
          "key": "crazy:glassdoor",
          "algo_type": "crazy",
          "algo_id": "glassdoor",
          "name": "Glassdoor Misery Gradient",
          "family": "labor_jobs",
          "status": "sandbox",
          "evidence_class": "needs_history",
          "rebalance_frequency": "monthly",
          "ytd_pct": 0.0,
          "days_running": 98,
          "beat_spy": false,
          "spy_pct": 8.95,
          "alpha_pct": -8.95,
          "ret_30d_pct": 0.0,
          "spy_delta_30d_pct": -8.19,
          "last_snapshot": "2026-05-13",
          "new_algo_date": null,
          "comparator": null
        },
        {
          "schema_version": "v1",
          "key": "crazy:daily-jump-in-rss-news-counts-mentioning-labor-strike-signal",
          "algo_type": "crazy",
          "algo_id": "daily-jump-in-rss-news-counts-mentioning-labor-strike-signal",
          "name": "Daily Jump In Rss News Counts Mentioning Labor Strike Signals Imminent Industrial Disruption",
          "family": "labor_jobs",
          "status": "sandbox",
          "evidence_class": "needs_history",
          "rebalance_frequency": "daily",
          "ytd_pct": 0.0,
          "days_running": 69,
          "beat_spy": false,
          "spy_pct": 8.95,
          "alpha_pct": -8.95,
          "ret_30d_pct": 0.0,
          "spy_delta_30d_pct": -8.19,
          "last_snapshot": "2026-05-13",
          "new_algo_date": null,
          "comparator": {
            "primary_etf": "XLI",
            "signals": {
              "momentum_5d": {
                "direction": "DOWN",
                "confidence": 0.368,
                "return_pct": -1.838
              },
              "momentum_20d": {
                "direction": "UP",
                "confidence": 0.285,
                "return_pct": 1.425
              }
            },
            "summary": "mixed"
          }
        }
      ]
    },
    "local_economy_weirdness": {
      "family": "local_economy_weirdness",
      "count": 20,
      "by_status": {
        "live_only": 11,
        "sandbox": 9
      },
      "by_evidence_class": {
        "live_receipts_only": 11,
        "needs_history": 9
      },
      "leaders": [
        {
          "schema_version": "v1",
          "key": "crazy:earthquake-aftershock-insurance-claims-spike",
          "algo_type": "crazy",
          "algo_id": "earthquake-aftershock-insurance-claims-spike",
          "name": "Earthquake Aftershock Insurance Claims Spike",
          "family": "local_economy_weirdness",
          "status": "live_only",
          "evidence_class": "live_receipts_only",
          "rebalance_frequency": "daily",
          "ytd_pct": 0.07,
          "days_running": 76,
          "beat_spy": false,
          "spy_pct": 8.95,
          "alpha_pct": -8.88,
          "ret_30d_pct": 0.0,
          "spy_delta_30d_pct": -8.19,
          "last_snapshot": "2026-05-13",
          "new_algo_date": null,
          "comparator": {
            "primary_etf": "XLF",
            "signals": {
              "momentum_5d": {
                "direction": "DOWN",
                "confidence": 0.328,
                "return_pct": -1.64
              },
              "momentum_20d": {
                "direction": "DOWN",
                "confidence": 0.452,
                "return_pct": -2.262
              }
            },
            "summary": "mixed"
          }
        },
        {
          "schema_version": "v1",
          "key": "crazy:daily-spike-in-usgs-earthquake-activity-near-key-industrial-",
          "algo_type": "crazy",
          "algo_id": "daily-spike-in-usgs-earthquake-activity-near-key-industrial-",
          "name": "Daily Spike In Usgs Earthquake Activity Near Key Industrial Hubs",
          "family": "local_economy_weirdness",
          "status": "live_only",
          "evidence_class": "live_receipts_only",
          "rebalance_frequency": "daily",
          "ytd_pct": 0.02,
          "days_running": 71,
          "beat_spy": false,
          "spy_pct": 8.95,
          "alpha_pct": -8.94,
          "ret_30d_pct": 0.0,
          "spy_delta_30d_pct": -8.19,
          "last_snapshot": "2026-05-13",
          "new_algo_date": null,
          "comparator": {
            "primary_etf": "XLI",
            "signals": {
              "momentum_5d": {
                "direction": "DOWN",
                "confidence": 0.368,
                "return_pct": -1.838
              },
              "momentum_20d": {
                "direction": "UP",
                "confidence": 0.285,
                "return_pct": 1.425
              }
            },
            "summary": "mixed"
          }
        },
        {
          "schema_version": "v1",
          "key": "crazy:daily-jump-in-google-trends-for-emergency-plumber-signals-ri",
          "algo_type": "crazy",
          "algo_id": "daily-jump-in-google-trends-for-emergency-plumber-signals-ri",
          "name": "Daily Jump In Google Trends For Emergency Plumber Signals Rising Local Economy Stress Benefiting Staples",
          "family": "local_economy_weirdness",
          "status": "live_only",
          "evidence_class": "live_receipts_only",
          "rebalance_frequency": "daily",
          "ytd_pct": 0.0,
          "days_running": 68,
          "beat_spy": false,
          "spy_pct": 8.95,
          "alpha_pct": -8.95,
          "ret_30d_pct": 0.0,
          "spy_delta_30d_pct": -8.19,
          "last_snapshot": "2026-05-13",
          "new_algo_date": null,
          "comparator": {
            "primary_etf": "XLP",
            "signals": {
              "momentum_5d": {
                "direction": "UP",
                "confidence": 0.114,
                "return_pct": 0.57
              },
              "momentum_20d": {
                "direction": "UP",
                "confidence": 0.903,
                "return_pct": 4.515
              }
            },
            "summary": "both_up"
          }
        },
        {
          "schema_version": "v1",
          "key": "crazy:craigslist",
          "algo_type": "crazy",
          "algo_id": "craigslist",
          "name": "Craigslist Desperation Index",
          "family": "local_economy_weirdness",
          "status": "sandbox",
          "evidence_class": "needs_history",
          "rebalance_frequency": "weekly",
          "ytd_pct": 0.0,
          "days_running": 98,
          "beat_spy": false,
          "spy_pct": 8.95,
          "alpha_pct": -8.95,
          "ret_30d_pct": 0.0,
          "spy_delta_30d_pct": -8.19,
          "last_snapshot": "2026-05-13",
          "new_algo_date": null,
          "comparator": null
        },
        {
          "schema_version": "v1",
          "key": "crazy:calls311",
          "algo_type": "crazy",
          "algo_id": "calls311",
          "name": "311 Call Rotation",
          "family": "local_economy_weirdness",
          "status": "sandbox",
          "evidence_class": "needs_history",
          "rebalance_frequency": "weekly",
          "ytd_pct": 0.0,
          "days_running": 98,
          "beat_spy": false,
          "spy_pct": 8.95,
          "alpha_pct": -8.95,
          "ret_30d_pct": 0.0,
          "spy_delta_30d_pct": -8.19,
          "last_snapshot": "2026-05-13",
          "new_algo_date": null,
          "comparator": null
        }
      ]
    },
    "macro_input_pressure": {
      "family": "macro_input_pressure",
      "count": 61,
      "by_status": {
        "backtest_weak": 1,
        "live_only": 16,
        "parked": 2,
        "sandbox": 42
      },
      "by_evidence_class": {
        "live_receipts_only": 16,
        "needs_history": 40,
        "pending_seed": 2,
        "v1_backtested": 3
      },
      "leaders": [
        {
          "schema_version": "v1",
          "key": "crazy:copper-momentum",
          "algo_type": "crazy",
          "algo_id": "copper-momentum",
          "name": "Copper Momentum",
          "family": "macro_input_pressure",
          "status": "live_only",
          "evidence_class": "live_receipts_only",
          "rebalance_frequency": "monthly",
          "ytd_pct": 0.12,
          "days_running": 98,
          "beat_spy": false,
          "spy_pct": 8.95,
          "alpha_pct": -8.84,
          "ret_30d_pct": 0.12,
          "spy_delta_30d_pct": -8.08,
          "last_snapshot": "2026-05-13",
          "new_algo_date": null,
          "comparator": null
        },
        {
          "schema_version": "v1",
          "key": "crazy:earthquake-aftershock-amplifier",
          "algo_type": "crazy",
          "algo_id": "earthquake-aftershock-amplifier",
          "name": "Earthquake Aftershock Amplifier",
          "family": "macro_input_pressure",
          "status": "live_only",
          "evidence_class": "live_receipts_only",
          "rebalance_frequency": "daily",
          "ytd_pct": 0.05,
          "days_running": 92,
          "beat_spy": false,
          "spy_pct": 8.95,
          "alpha_pct": -8.91,
          "ret_30d_pct": 0.0,
          "spy_delta_30d_pct": -8.19,
          "last_snapshot": "2026-05-13",
          "new_algo_date": null,
          "comparator": {
            "primary_etf": "XLE",
            "signals": {
              "momentum_5d": {
                "direction": "UP",
                "confidence": 0.221,
                "return_pct": 1.105
              },
              "momentum_20d": {
                "direction": "UP",
                "confidence": 0.671,
                "return_pct": 3.354
              }
            },
            "summary": "both_up"
          }
        },
        {
          "schema_version": "v1",
          "key": "crazy:semiconductor-moonshot-warning",
          "algo_type": "crazy",
          "algo_id": "semiconductor-moonshot-warning",
          "name": "Semiconductor Moonshot Warning",
          "family": "macro_input_pressure",
          "status": "backtest_weak",
          "evidence_class": "v1_backtested",
          "rebalance_frequency": "daily",
          "ytd_pct": 0.04,
          "days_running": 92,
          "beat_spy": false,
          "spy_pct": 8.95,
          "alpha_pct": -8.91,
          "ret_30d_pct": 0.04,
          "spy_delta_30d_pct": -8.15,
          "last_snapshot": "2026-05-13",
          "new_algo_date": null,
          "comparator": {
            "primary_etf": "XLK",
            "signals": {
              "momentum_5d": {
                "direction": "UP",
                "confidence": 0.802,
                "return_pct": 4.011
              },
              "momentum_20d": {
                "direction": "UP",
                "confidence": 1.0,
                "return_pct": 17.665
              }
            },
            "summary": "both_up"
          }
        },
        {
          "schema_version": "v1",
          "key": "crazy:crypto-capitulation-countdown",
          "algo_type": "crazy",
          "algo_id": "crypto-capitulation-countdown",
          "name": "Crypto Capitulation Countdown",
          "family": "macro_input_pressure",
          "status": "sandbox",
          "evidence_class": "v1_backtested",
          "rebalance_frequency": "daily",
          "ytd_pct": 0.0,
          "days_running": 92,
          "beat_spy": false,
          "spy_pct": 8.95,
          "alpha_pct": -8.95,
          "ret_30d_pct": 0.0,
          "spy_delta_30d_pct": -8.19,
          "last_snapshot": "2026-05-13",
          "new_algo_date": null,
          "comparator": {
            "primary_etf": "XLC",
            "signals": {
              "momentum_5d": {
                "direction": "DOWN",
                "confidence": 0.101,
                "return_pct": -0.503
              },
              "momentum_20d": {
                "direction": "DOWN",
                "confidence": 0.102,
                "return_pct": -0.511
              }
            },
            "summary": "mixed"
          }
        },
        {
          "schema_version": "v1",
          "key": "crazy:cloud-storage-demand-surge",
          "algo_type": "crazy",
          "algo_id": "cloud-storage-demand-surge",
          "name": "Cloud Storage Demand Surge",
          "family": "macro_input_pressure",
          "status": "sandbox",
          "evidence_class": "needs_history",
          "rebalance_frequency": "daily",
          "ytd_pct": 0.0,
          "days_running": 98,
          "beat_spy": false,
          "spy_pct": 8.95,
          "alpha_pct": -8.95,
          "ret_30d_pct": 0.0,
          "spy_delta_30d_pct": -8.19,
          "last_snapshot": "2026-05-13",
          "new_algo_date": null,
          "comparator": null
        }
      ]
    },
    "political_insider_filing": {
      "family": "political_insider_filing",
      "count": 18,
      "by_status": {
        "backtest_weak": 3,
        "live_only": 7,
        "parked": 2,
        "sandbox": 6
      },
      "by_evidence_class": {
        "live_receipts_only": 6,
        "needs_history": 5,
        "pending_seed": 2,
        "v1_backtested": 5
      },
      "leaders": [
        {
          "schema_version": "v1",
          "key": "crazy:insider-trading-signals",
          "algo_type": "crazy",
          "algo_id": "insider-trading-signals",
          "name": "Insider Trading Signals",
          "family": "political_insider_filing",
          "status": "live_only",
          "evidence_class": "live_receipts_only",
          "rebalance_frequency": "weekly",
          "ytd_pct": 1.11,
          "days_running": 98,
          "beat_spy": false,
          "spy_pct": 8.95,
          "alpha_pct": -7.84,
          "ret_30d_pct": 1.11,
          "spy_delta_30d_pct": -7.08,
          "last_snapshot": "2026-05-13",
          "new_algo_date": null,
          "comparator": null
        },
        {
          "schema_version": "v1",
          "key": "crazy:finra-dark-pool-signal",
          "algo_type": "crazy",
          "algo_id": "finra-dark-pool-signal",
          "name": "FINRA Dark Pool Signal",
          "family": "political_insider_filing",
          "status": "live_only",
          "evidence_class": "live_receipts_only",
          "rebalance_frequency": "weekly",
          "ytd_pct": 0.14,
          "days_running": 89,
          "beat_spy": false,
          "spy_pct": 8.95,
          "alpha_pct": -8.81,
          "ret_30d_pct": 0.14,
          "spy_delta_30d_pct": -8.05,
          "last_snapshot": "2026-05-13",
          "new_algo_date": null,
          "comparator": null
        },
        {
          "schema_version": "v1",
          "key": "crazy:materials-sector-weekly-positive-correlation-breakdown-with-",
          "algo_type": "crazy",
          "algo_id": "materials-sector-weekly-positive-correlation-breakdown-with-",
          "name": "Materials Sector Weekly Positive Correlation Breakdown With Xlb",
          "family": "political_insider_filing",
          "status": "live_only",
          "evidence_class": "v1_backtested",
          "rebalance_frequency": "weekly",
          "ytd_pct": 0.03,
          "days_running": 92,
          "beat_spy": false,
          "spy_pct": 8.95,
          "alpha_pct": -8.93,
          "ret_30d_pct": 0.0,
          "spy_delta_30d_pct": -8.19,
          "last_snapshot": "2026-05-13",
          "new_algo_date": null,
          "comparator": {
            "primary_etf": "XLB",
            "signals": {
              "momentum_5d": {
                "direction": "DOWN",
                "confidence": 0.134,
                "return_pct": -0.668
              },
              "momentum_20d": {
                "direction": "UP",
                "confidence": 0.265,
                "return_pct": 1.323
              }
            },
            "summary": "mixed"
          }
        },
        {
          "schema_version": "v1",
          "key": "crazy:staples-sector-drawdown-rapid-recovery",
          "algo_type": "crazy",
          "algo_id": "staples-sector-drawdown-rapid-recovery",
          "name": "Staples Sector Drawdown Rapid Recovery",
          "family": "political_insider_filing",
          "status": "backtest_weak",
          "evidence_class": "v1_backtested",
          "rebalance_frequency": "daily",
          "ytd_pct": 0.02,
          "days_running": 92,
          "beat_spy": false,
          "spy_pct": 8.95,
          "alpha_pct": -8.93,
          "ret_30d_pct": 0.0,
          "spy_delta_30d_pct": -8.19,
          "last_snapshot": "2026-05-13",
          "new_algo_date": null,
          "comparator": {
            "primary_etf": "XLP",
            "signals": {
              "momentum_5d": {
                "direction": "UP",
                "confidence": 0.114,
                "return_pct": 0.57
              },
              "momentum_20d": {
                "direction": "UP",
                "confidence": 0.903,
                "return_pct": 4.515
              }
            },
            "summary": "both_up"
          }
        },
        {
          "schema_version": "v1",
          "key": "crazy:bankruptcy-filing-rate",
          "algo_type": "crazy",
          "algo_id": "bankruptcy-filing-rate",
          "name": "Bankruptcy Filing Rate",
          "family": "political_insider_filing",
          "status": "sandbox",
          "evidence_class": "needs_history",
          "rebalance_frequency": "monthly",
          "ytd_pct": 0.0,
          "days_running": 98,
          "beat_spy": false,
          "spy_pct": 8.95,
          "alpha_pct": -8.95,
          "ret_30d_pct": 0.0,
          "spy_delta_30d_pct": -8.19,
          "last_snapshot": "2026-05-13",
          "new_algo_date": null,
          "comparator": null
        }
      ]
    },
    "travel_mobility": {
      "family": "travel_mobility",
      "count": 15,
      "by_status": {
        "live_only": 3,
        "sandbox": 12
      },
      "by_evidence_class": {
        "live_receipts_only": 3,
        "needs_history": 12
      },
      "leaders": [
        {
          "schema_version": "v1",
          "key": "crazy:uber-mobility",
          "algo_type": "crazy",
          "algo_id": "uber-mobility",
          "name": "Uber Mobility Index",
          "family": "travel_mobility",
          "status": "live_only",
          "evidence_class": "live_receipts_only",
          "rebalance_frequency": "weekly",
          "ytd_pct": 4.16,
          "days_running": 98,
          "beat_spy": false,
          "spy_pct": 8.95,
          "alpha_pct": -4.8,
          "ret_30d_pct": 4.16,
          "spy_delta_30d_pct": -4.03,
          "last_snapshot": "2026-05-13",
          "new_algo_date": null,
          "comparator": null
        },
        {
          "schema_version": "v1",
          "key": "crazy:airport-shopping-spree",
          "algo_type": "crazy",
          "algo_id": "airport-shopping-spree",
          "name": "Airport Shopping Spree",
          "family": "travel_mobility",
          "status": "sandbox",
          "evidence_class": "needs_history",
          "rebalance_frequency": "daily",
          "ytd_pct": 0.0,
          "days_running": 98,
          "beat_spy": false,
          "spy_pct": 8.95,
          "alpha_pct": -8.95,
          "ret_30d_pct": 0.0,
          "spy_delta_30d_pct": -8.19,
          "last_snapshot": "2026-05-13",
          "new_algo_date": null,
          "comparator": null
        },
        {
          "schema_version": "v1",
          "key": "crazy:airport-security-surge",
          "algo_type": "crazy",
          "algo_id": "airport-security-surge",
          "name": "Airport Security Surge",
          "family": "travel_mobility",
          "status": "sandbox",
          "evidence_class": "needs_history",
          "rebalance_frequency": "daily",
          "ytd_pct": 0.0,
          "days_running": 96,
          "beat_spy": false,
          "spy_pct": 8.95,
          "alpha_pct": -8.95,
          "ret_30d_pct": 0.0,
          "spy_delta_30d_pct": -8.19,
          "last_snapshot": "2026-05-13",
          "new_algo_date": null,
          "comparator": {
            "primary_etf": "XLI",
            "signals": {
              "momentum_5d": {
                "direction": "DOWN",
                "confidence": 0.368,
                "return_pct": -1.838
              },
              "momentum_20d": {
                "direction": "UP",
                "confidence": 0.285,
                "return_pct": 1.425
              }
            },
            "summary": "mixed"
          }
        },
        {
          "schema_version": "v1",
          "key": "crazy:airline-load-factor",
          "algo_type": "crazy",
          "algo_id": "airline-load-factor",
          "name": "Airline Load Factor Proxy",
          "family": "travel_mobility",
          "status": "sandbox",
          "evidence_class": "needs_history",
          "rebalance_frequency": "monthly",
          "ytd_pct": 0.0,
          "days_running": 98,
          "beat_spy": false,
          "spy_pct": 8.95,
          "alpha_pct": -8.95,
          "ret_30d_pct": 0.0,
          "spy_delta_30d_pct": -8.19,
          "last_snapshot": "2026-05-13",
          "new_algo_date": null,
          "comparator": null
        },
        {
          "schema_version": "v1",
          "key": "crazy:airline-fuel-cost-volatility-expansion",
          "algo_type": "crazy",
          "algo_id": "airline-fuel-cost-volatility-expansion",
          "name": "Airline Fuel Cost Volatility Expansion",
          "family": "travel_mobility",
          "status": "sandbox",
          "evidence_class": "needs_history",
          "rebalance_frequency": "daily",
          "ytd_pct": 0.0,
          "days_running": 68,
          "beat_spy": false,
          "spy_pct": 8.95,
          "alpha_pct": -8.95,
          "ret_30d_pct": 0.0,
          "spy_delta_30d_pct": -8.19,
          "last_snapshot": "2026-05-13",
          "new_algo_date": null,
          "comparator": {
            "primary_etf": "XLY",
            "signals": {
              "momentum_5d": {
                "direction": "DOWN",
                "confidence": 0.192,
                "return_pct": -0.959
              },
              "momentum_20d": {
                "direction": "UP",
                "confidence": 0.091,
                "return_pct": 0.457
              }
            },
            "summary": "mixed"
          }
        }
      ]
    }
  }
}
