{
  "schema_version": "v1",
  "generated_at": "2026-06-24T23:58:11Z",
  "algos": [
    {
      "schema_version": "v1",
      "key": "normal:simple_monthly",
      "algo_type": "normal",
      "algo_id": "simple_monthly",
      "name": "Quantified Simple Monthly Rotation",
      "family": "core_rotation",
      "status": "promoted",
      "evidence_class": "live_receipts_only",
      "rebalance_frequency": "monthly_eom",
      "thesis_one_liner": "Quantified Simple Monthly Rotation tests whether systematic price rotation can capture persistent sector momentum better than passive market exposure.",
      "thesis_source": "derived",
      "ytd_pct": 7.73,
      "days_running": 135,
      "beat_spy": false,
      "spy_pct": 7.9,
      "alpha_pct": -0.17,
      "ret_30d_pct": -4.74,
      "spy_delta_30d_pct": -2.68,
      "last_snapshot": "2026-06-24",
      "new_algo_date": null,
      "comparator": null
    },
    {
      "schema_version": "v1",
      "key": "normal:baileymol",
      "algo_type": "normal",
      "algo_id": "baileymol",
      "name": "Algo Baileymol (Chaos Monger)",
      "family": "core_rotation",
      "status": "promoted",
      "evidence_class": "v1_backtested",
      "rebalance_frequency": "weekly",
      "thesis_one_liner": "Algo Baileymol (Chaos Monger) tests whether systematic price rotation can capture persistent sector momentum better than passive market exposure.",
      "thesis_source": "derived",
      "ytd_pct": 4.44,
      "days_running": 135,
      "beat_spy": false,
      "spy_pct": 7.9,
      "alpha_pct": -3.46,
      "ret_30d_pct": -3.44,
      "spy_delta_30d_pct": -1.38,
      "last_snapshot": "2026-06-24",
      "new_algo_date": null,
      "comparator": null
    },
    {
      "schema_version": "v1",
      "key": "normal:dmsr",
      "algo_type": "normal",
      "algo_id": "dmsr",
      "name": "Antonacci Dual Momentum Sector Rotation",
      "family": "core_rotation",
      "status": "promoted",
      "evidence_class": "live_receipts_only",
      "rebalance_frequency": "monthly_eom",
      "thesis_one_liner": "Antonacci Dual Momentum Sector Rotation tests whether systematic price rotation can capture persistent sector momentum better than passive market exposure.",
      "thesis_source": "derived",
      "ytd_pct": 4.17,
      "days_running": 135,
      "beat_spy": false,
      "spy_pct": 7.9,
      "alpha_pct": -3.73,
      "ret_30d_pct": -2.54,
      "spy_delta_30d_pct": -0.48,
      "last_snapshot": "2026-06-24",
      "new_algo_date": null,
      "comparator": null
    },
    {
      "schema_version": "v1",
      "key": "normal:faber",
      "algo_type": "normal",
      "algo_id": "faber",
      "name": "Faber Momentum Rotation",
      "family": "core_rotation",
      "status": "promoted",
      "evidence_class": "v1_backtested",
      "rebalance_frequency": "monthly_eom",
      "thesis_one_liner": "Faber Momentum Rotation tests whether systematic price rotation can capture persistent sector momentum better than passive market exposure.",
      "thesis_source": "derived",
      "ytd_pct": 2.97,
      "days_running": 135,
      "beat_spy": false,
      "spy_pct": 7.9,
      "alpha_pct": -4.93,
      "ret_30d_pct": -4.89,
      "spy_delta_30d_pct": -2.83,
      "last_snapshot": "2026-06-24",
      "new_algo_date": null,
      "comparator": null
    },
    {
      "schema_version": "v1",
      "key": "normal:biscotti",
      "algo_type": "normal",
      "algo_id": "biscotti",
      "name": "Algo Biscotti (Unconditional Loyalty)",
      "family": "core_rotation",
      "status": "promoted",
      "evidence_class": "v1_backtested",
      "rebalance_frequency": "monthly_eom",
      "thesis_one_liner": "Algo Biscotti (Unconditional Loyalty) tests whether systematic price rotation can capture persistent sector momentum better than passive market exposure.",
      "thesis_source": "derived",
      "ytd_pct": 1.36,
      "days_running": 135,
      "beat_spy": false,
      "spy_pct": 7.9,
      "alpha_pct": -6.54,
      "ret_30d_pct": 1.33,
      "spy_delta_30d_pct": 3.39,
      "last_snapshot": "2026-06-24",
      "new_algo_date": null,
      "comparator": null
    }
  ]
}
